Workbook

Sheet 明細
A1: 利用日 | B1: 利用者 | C1: ご利用先 | D1: カテゴリ | E1: 支払方法 | F1: 金額 | G1: 備考
A2: 2026-06-10 | B2: 家族1（奥様） | C2: シーセイ | D2: その他 | E2: 1回 | F2: 3228 | G2: ポイント2倍対象／店舗名から用途不明・要確認
A3: 2026-06-12 | B3: 家族1（奥様） | C3: 阪急オアシス | D3: スーパー・食料品 | E3: 1回 | F3: 726
A4: 2026-06-12 | B4: 家族1（奥様） | C4: 阪急オアシス | D4: スーパー・食料品 | E4: 1回 | F4: 2208
A5: 2026-06-13 | B5: 本人 | C5: イオンumie | D5: ショッピングモール・百貨店 | E5: 1回 | F5: 5459 | G5: ポイント10倍対象
A6: 2026-06-13 | B6: 家族1（奥様） | C6: ホームセンターコーナンハーバ | D6: 日用品・インテリア | E6: 1回 | F6: 4853
A7: 2026-06-13 | B7: 家族1（奥様） | C7: 神戸ハーバーランドumie | D7: ショッピングモール・百貨店 | E7: 1回 | F7: 648
A8: 2026-06-13 | B8: 家族1（奥様） | C8: ダイソー | D8: 日用品・インテリア | E8: 1回 | F8: 220
A9: 2026-06-13 | B9: 家族1（奥様） | C9: ダイソー | D9: 日用品・インテリア | E9: 1回 | F9: 550
A10: 2026-06-13 | B10: 家族1（奥様） | C10: ホームドライ フラワーロード | D10: 日用品・インテリア | E10: 1回 | F10: 8320 | G10: クリーニング
A11: 2026-06-14 | B11: 家族1（奥様） | C11: コウベコーヒーモノガタリ | D11: 外食・カフェ | E11: 1回 | F11: 2440
A12: 2026-06-14 | B12: 本人 | C12: ボアフロッテ ティーピー | D12: その他 | E12: 1回 | F12: 17820 | G12: 店舗名から用途不明・要確認
A13: 2026-06-15 | B13: 本人 | C13: KOHYO三宮 | D13: スーパー・食料品 | E13: 1回 | F13: 1307 | G13: ポイント2倍対象
A14: 2026-06-19 | B14: 本人 | C14: KOHYO三宮 | D14: スーパー・食料品 | E14: 1回 | F14: 1953 | G14: ポイント2倍対象
A15: 2026-06-21 | B15: 家族1（奥様） | C15: ジーユー | D15: ファッション・美容 | E15: 1回 | F15: 4790
A16: 2026-07-02 | B16: 家族1（奥様） | C16: アップルドットコム | D16: ネットショッピング | E16: 1回 | F16: 6490
A17: 2026-07-08 | B17: 本人 | C17: ベルトラ コーポ | D17: 旅行・宿泊 | E17: 1回 | F17: -9596 | G17: ご返品
A18: 2026-07-08 | B18: 本人 | C18: ベルトラ コーポ | D18: 旅行・宿泊 | E18: 1回 | F18: -9596 | G18: ご返品
A19: 2026-07-08 | B19: 本人 | C19: ベルトラ コーポ | D19: 旅行・宿泊 | E19: 1回 | F19: -36464 | G19: ご返品
A20: 2026-07-10 | B20: 本人 | C20: 7月事務手数料 | D20: 手数料・利息 | E20: 1回 | F20: 440 | G20: 10%税込
E22: 今回ご利用金額合計 | F22: =SUM(F2:F20)
A24: ※上記の明細合計（5,796円）と、実際の請求金額（34,473円、支払日2026年8月3日）には差があります。明細書内の「7月10日現在残高」欄も34,473円となっており、明細に記載されない繰越・別枠の請求が含まれている可能性があります。原本PDFで要確認。

Sheet 利用者別サマリー
A1: イオンゴールドカード 2026年8月お支払分（利用期間 6/10〜7/10）利用者別集計
A3: 利用者 | B3: 金額 | C3: 件数
A4: 本人 | B4: =SUMIF(明細!$B$2:$B$20,$A4,明細!$F$2:$F$20) | C4: =COUNTIF(明細!$B$2:$B$20,$A4)
A5: 家族1（奥様） | B5: =SUMIF(明細!$B$2:$B$20,$A5,明細!$F$2:$F$20) | C5: =COUNTIF(明細!$B$2:$B$20,$A5)
A6: 合計 | B6: =SUM(B4:B5) | C6: =SUM(C4:C5)
A8: 参考：今回ご請求金額（口座引落額・2026/8/3） | B8: 34473

Sheet カテゴリ別集計
A1: カテゴリ別集計（2026年8月お支払分）
A3: カテゴリ | B3: 金額 | C3: 構成比
A4: その他 | B4: =SUMIF(明細!$D$2:$D$20,$A4,明細!$F$2:$F$20) | C4: =B4/$B$13
A5: ショッピングモール・百貨店 | B5: =SUMIF(明細!$D$2:$D$20,$A5,明細!$F$2:$F$20) | C5: =B5/$B$13
A6: スーパー・食料品 | B6: =SUMIF(明細!$D$2:$D$20,$A6,明細!$F$2:$F$20) | C6: =B6/$B$13
A7: ネットショッピング | B7: =SUMIF(明細!$D$2:$D$20,$A7,明細!$F$2:$F$20) | C7: =B7/$B$13
A8: ファッション・美容 | B8: =SUMIF(明細!$D$2:$D$20,$A8,明細!$F$2:$F$20) | C8: =B8/$B$13
A9: 外食・カフェ | B9: =SUMIF(明細!$D$2:$D$20,$A9,明細!$F$2:$F$20) | C9: =B9/$B$13
A10: 手数料・利息 | B10: =SUMIF(明細!$D$2:$D$20,$A10,明細!$F$2:$F$20) | C10: =B10/$B$13
A11: 旅行・宿泊 | B11: =SUMIF(明細!$D$2:$D$20,$A11,明細!$F$2:$F$20) | C11: =B11/$B$13
A12: 日用品・インテリア | B12: =SUMIF(明細!$D$2:$D$20,$A12,明細!$F$2:$F$20) | C12: =B12/$B$13
A13: 合計 | B13: =SUM(B4:B12)
