Workbook

Sheet 明細
A1: 利用日 | B1: 利用店名 | C1: カテゴリ | D1: 利用者 | E1: 支払方法 | F1: 金額 | G1: お支払月
A2: 2025/11/30 | B2: ＵＱ ｍｏｂｉｌｅご利用料金 | C2: 通信費・サブスク | D2: 本人* | E2: 1回払い | F2: 3743 | G2: 1月
A3: 2025/12/01 | B3: GOOGLE*CLOUD 8V57 | C3: 通信費・サブスク | D3: 本人* | E3: 1回払い | F3: 1 | G3: 1月
A4: 2025/12/05 | B4: ﾈｯﾄﾌﾘｯｸｽ | C4: 通信費・サブスク | D4: 本人* | E4: 1回払い | F4: 890 | G4: 1月
A5: 2025/12/08 | B5: お名前．ｃｏｍレンタルサーバー | C5: 通信費・サブスク | D5: 本人* | E5: 1回払い | F5: 484 | G5: 1月
A6: 2025/12/14 | B6: 楽天キャッシュ チャージ | C6: 電子マネー・チャージ | D6: 本人* | E6: 1回払い | F6: 29559 | G6: 1月
A7: 2025/12/16 | B7: 楽天証券投信積立０．５％〜 | C7: 投資 | D7: 本人* | E7: 1回払い | F7: 49994 | G7: 1月
A8: 2025/12/30 | B8: ＥＴＣカード売上 | C8: 交通費 | D8: ETC* | E8: 1回払い | F8: 5960 | G8: 2月
A9: 2025/12/31 | B9: ＵＱ ｍｏｂｉｌｅご利用料金 | C9: 通信費・サブスク | D9: 本人* | E9: 1回払い | F9: 3750 | G9: 2月
A10: 2025/12/31 | B10: ＥＴＣカード売上 | C10: 交通費 | D10: ETC* | E10: 1回払い | F10: 2430 | G10: 2月
A11: 2025/12/31 | B11: ＥＴＣカード売上 | C11: 交通費 | D11: ETC* | E11: 1回払い | F11: 710 | G11: 2月
A12: 2026/01/01 | B12: ＥＴＣカード売上 | C12: 交通費 | D12: ETC* | E12: 1回払い | F12: 4180 | G12: 2月
A13: 2026/01/02 | B13: ＥＴＣカード売上 | C13: 交通費 | D13: ETC* | E13: 1回払い | F13: 940 | G13: 2月
... A73: 2026/06/13 | B73: 楽天キャッシュ チャージ | C73: 電子マネー・チャージ | D73: 本人* | E73: 1回払い | F73: 2293 | G73: 7月
C74: 合計 | F74: =SUM(F2:F73)

Sheet 月別サマリー
A1: 楽天カード ご利用明細 月別×カテゴリ集計（お支払月ベース）
A3: カテゴリ | B3: 1月(支払) | C3: 2月(支払) | D3: 3月(支払) | E3: 4月(支払) | F3: 5月(支払) | G3: 6月(支払) | H3: 7月(支払) | I3: 合計
A4: 投資 | B4: =SUMIFS(明細!$F$2:$F$73,明細!$C$2:$C$73,$A4,明細!$G$2:$G$73,B$3) | C4: =SUMIFS(明細!$F$2:$F$73,明細!$C$2:$C$73,$A4,明細!$G$2:$G$73,C$3) | D4: =SUMIFS(明細!$F$2:$F$73,明細!$C$2:$C$73,$A4,明細!$G$2:$G$73,D$3) | E4: =SUMIFS(明細!$F$2:$F$73,明細!$C$2:$C$73,$A4,明細!$G$2:$G$73,E$3) | F4: =SUMIFS(明細!$F$2:$F$73,明細!$C$2:$C$73,$A4,明細!$G$2:$G$73,F$3) | G4: =SUMIFS(明細!$F$2:$F$73,明細!$C$2:$C$73,$A4,明細!$G$2:$G$73,G$3) | H4: =SUMIFS(明細!$F$2:$F$73,明細!$C$2:$C$73,$A4,明細!$G$2:$G$73,H$3) | I4: =SUM(B4:H4)
A5: 電子マネー・チャージ | B5: =SUMIFS(明細!$F$2:$F$73,明細!$C$2:$C$73,$A5,明細!$G$2:$G$73,B$3) | C5: =SUMIFS(明細!$F$2:$F$73,明細!$C$2:$C$73,$A5,明細!$G$2:$G$73,C$3) | D5: =SUMIFS(明細!$F$2:$F$73,明細!$C$2:$C$73,$A5,明細!$G$2:$G$73,D$3) | E5: =SUMIFS(明細!$F$2:$F$73,明細!$C$2:$C$73,$A5,明細!$G$2:$G$73,E$3) | F5: =SUMIFS(明細!$F$2:$F$73,明細!$C$2:$C$73,$A5,明細!$G$2:$G$73,F$3) | G5: =SUMIFS(明細!$F$2:$F$73,明細!$C$2:$C$73,$A5,明細!$G$2:$G$73,G$3) | H5: =SUMIFS(明細!$F$2:$F$73,明細!$C$2:$C$73,$A5,明細!$G$2:$G$73,H$3) | I5: =SUM(B5:H5)
A6: 通信費・サブスク | B6: =SUMIFS(明細!$F$2:$F$73,明細!$C$2:$C$73,$A6,明細!$G$2:$G$73,B$3) | C6: =SUMIFS(明細!$F$2:$F$73,明細!$C$2:$C$73,$A6,明細!$G$2:$G$73,C$3) | D6: =SUMIFS(明細!$F$2:$F$73,明細!$C$2:$C$73,$A6,明細!$G$2:$G$73,D$3) | E6: =SUMIFS(明細!$F$2:$F$73,明細!$C$2:$C$73,$A6,明細!$G$2:$G$73,E$3) | F6: =SUMIFS(明細!$F$2:$F$73,明細!$C$2:$C$73,$A6,明細!$G$2:$G$73,F$3) | G6: =SUMIFS(明細!$F$2:$F$73,明細!$C$2:$C$73,$A6,明細!$G$2:$G$73,G$3) | H6: =SUMIFS(明細!$F$2:$F$73,明細!$C$2:$C$73,$A6,明細!$G$2:$G$73,H$3) | I6: =SUM(B6:H6)
A7: 交通費 | B7: =SUMIFS(明細!$F$2:$F$73,明細!$C$2:$C$73,$A7,明細!$G$2:$G$73,B$3) | C7: =SUMIFS(明細!$F$2:$F$73,明細!$C$2:$C$73,$A7,明細!$G$2:$G$73,C$3) | D7: =SUMIFS(明細!$F$2:$F$73,明細!$C$2:$C$73,$A7,明細!$G$2:$G$73,D$3) | E7: =SUMIFS(明細!$F$2:$F$73,明細!$C$2:$C$73,$A7,明細!$G$2:$G$73,E$3) | F7: =SUMIFS(明細!$F$2:$F$73,明細!$C$2:$C$73,$A7,明細!$G$2:$G$73,F$3) | G7: =SUMIFS(明細!$F$2:$F$73,明細!$C$2:$C$73,$A7,明細!$G$2:$G$73,G$3) | H7: =SUMIFS(明細!$F$2:$F$73,明細!$C$2:$C$73,$A7,明細!$G$2:$G$73,H$3) | I7: =SUM(B7:H7)
A8: ネットショッピング | B8: =SUMIFS(明細!$F$2:$F$73,明細!$C$2:$C$73,$A8,明細!$G$2:$G$73,B$3) | C8: =SUMIFS(明細!$F$2:$F$73,明細!$C$2:$C$73,$A8,明細!$G$2:$G$73,C$3) | D8: =SUMIFS(明細!$F$2:$F$73,明細!$C$2:$C$73,$A8,明細!$G$2:$G$73,D$3) | E8: =SUMIFS(明細!$F$2:$F$73,明細!$C$2:$C$73,$A8,明細!$G$2:$G$73,E$3) | F8: =SUMIFS(明細!$F$2:$F$73,明細!$C$2:$C$73,$A8,明細!$G$2:$G$73,F$3) | G8: =SUMIFS(明細!$F$2:$F$73,明細!$C$2:$C$73,$A8,明細!$G$2:$G$73,G$3) | H8: =SUMIFS(明細!$F$2:$F$73,明細!$C$2:$C$73,$A8,明細!$G$2:$G$73,H$3) | I8: =SUM(B8:H8)
A9: スーパー・食料品 | B9: =SUMIFS(明細!$F$2:$F$73,明細!$C$2:$C$73,$A9,明細!$G$2:$G$73,B$3) | C9: =SUMIFS(明細!$F$2:$F$73,明細!$C$2:$C$73,$A9,明細!$G$2:$G$73,C$3) | D9: =SUMIFS(明細!$F$2:$F$73,明細!$C$2:$C$73,$A9,明細!$G$2:$G$73,D$3) | E9: =SUMIFS(明細!$F$2:$F$73,明細!$C$2:$C$73,$A9,明細!$G$2:$G$73,E$3) | F9: =SUMIFS(明細!$F$2:$F$73,明細!$C$2:$C$73,$A9,明細!$G$2:$G$73,F$3) | G9: =SUMIFS(明細!$F$2:$F$73,明細!$C$2:$C$73,$A9,明細!$G$2:$G$73,G$3) | H9: =SUMIFS(明細!$F$2:$F$73,明細!$C$2:$C$73,$A9,明細!$G$2:$G$73,H$3) | I9: =SUM(B9:H9)
A10: その他 | B10: =SUMIFS(明細!$F$2:$F$73,明細!$C$2:$C$73,$A10,明細!$G$2:$G$73,B$3) | C10: =SUMIFS(明細!$F$2:$F$73,明細!$C$2:$C$73,$A10,明細!$G$2:$G$73,C$3) | D10: =SUMIFS(明細!$F$2:$F$73,明細!$C$2:$C$73,$A10,明細!$G$2:$G$73,D$3) | E10: =SUMIFS(明細!$F$2:$F$73,明細!$C$2:$C$73,$A10,明細!$G$2:$G$73,E$3) | F10: =SUMIFS(明細!$F$2:$F$73,明細!$C$2:$C$73,$A10,明細!$G$2:$G$73,F$3) | G10: =SUMIFS(明細!$F$2:$F$73,明細!$C$2:$C$73,$A10,明細!$G$2:$G$73,G$3) | H10: =SUMIFS(明細!$F$2:$F$73,明細!$C$2:$C$73,$A10,明細!$G$2:$G$73,H$3) | I10: =SUM(B10:H10)
A11: 合計 | B11: =SUM(B4:B10) | C11: =SUM(C4:C10) | D11: =SUM(D4:D10) | E11: =SUM(E4:E10) | F11: =SUM(F4:F10) | G11: =SUM(G4:G10) | H11: =SUM(H4:H10) | I11: =SUM(I4:I10)
A13: 参考：各月の「ご請求金額」（明細書記載）。2月は調整額-23,044円・返金26,950円が発生したため、明細合計23,044円に対し請求額は0円。
A14: お支払月 | B14: お支払日 | C14: ご請求金額(明細書記載)
A15: 1月(支払) | B15: 2026/01/27 | C15: 84671
A16: 2月(支払) | B16: 2026/02/27 | C16: 0
A17: 3月(支払) | B17: 2026/03/27 | C17: 6126
A18: 4月(支払) | B18: 2026/04/27 | C18: 5119
A19: 5月(支払) | B19: 2026/05/27 | C19: 15596
A20: 6月(支払) | B20: 2026/06/29 | C20: 75147
A21: 7月(支払) | B21: 2026/07/27 | C21: 13154

Sheet カテゴリ別集計
A1: カテゴリ別集計（2026年1月〜7月支払 全体）
A3: カテゴリ | B3: 金額 | C3: 構成比
A4: 投資 | B4: =SUMIF(明細!$C$2:$C$73,$A4,明細!$F$2:$F$73) | C4: =B4/$B$11
A5: 電子マネー・チャージ | B5: =SUMIF(明細!$C$2:$C$73,$A5,明細!$F$2:$F$73) | C5: =B5/$B$11
A6: 通信費・サブスク | B6: =SUMIF(明細!$C$2:$C$73,$A6,明細!$F$2:$F$73) | C6: =B6/$B$11
A7: 交通費 | B7: =SUMIF(明細!$C$2:$C$73,$A7,明細!$F$2:$F$73) | C7: =B7/$B$11
A8: ネットショッピング | B8: =SUMIF(明細!$C$2:$C$73,$A8,明細!$F$2:$F$73) | C8: =B8/$B$11
A9: スーパー・食料品 | B9: =SUMIF(明細!$C$2:$C$73,$A9,明細!$F$2:$F$73) | C9: =B9/$B$11
A10: その他 | B10: =SUMIF(明細!$C$2:$C$73,$A10,明細!$F$2:$F$73) | C10: =B10/$B$11
A11: 合計 | B11: =SUM(B4:B10) | C11: =B11/B11
